dev_tips/__init__.py
dev_tips/main.py
dev_tips/tips/__init__.py
dev_tips/tips/tip_01.md
dev_tips/tips/tip_02.md
dev_tips/tips/tip_03.md
dev_tips/tips/tip_04.md
dev_tips/tips/tip_05.md
dev_tips/tips/tip_06.md
dev_tips/tips/tip_07.md
dev_tips/tips/tip_08.md
dev_tips/tips/tip_09.md
dev_tips/tips/tip_10.md
dev_tips/tips/tip_11.md
dev_tips/tips/tip_12.md
dev_tips/tips/tip_13.md
dev_tips/tips/tip_14.md
dev_tips/tips/tip_15.md
dev_tips/tips/tip_16.md
dev_tips/tips/tip_17.md
dev_tips/tips/tip_18.md
dev_tips/tips/tip_19.md
dev_tips/tips/tip_20.md
dev_tips/tips/tip_21.md
dev_tips/tips/tip_22.md
dev_tips/tips/tip_23.md
dev_tips/tips/tip_24.md
dev_tips/tips/tip_25.md
dev_tips/tips/tip_26.md
dev_tips/tips/tip_27.md
dev_tips/tips/tip_28.md
dev_tips/tips/tip_29.md
dev_tips/tips/tip_30.md
dev_tips/tips/tip_31.md
dev_tips/tips/tip_32.md
dev_tips/tips/tip_33.md
dev_tips/tips/tip_34.md
dev_tips/tips/tip_35.md
dev_tips/tips/tip_36.md
dev_tips/tips/tip_37.md
dev_tips/tips/tip_38.md
dev_tips/tips/tip_39.md
dev_tips/tips/tip_40.md
dev_tips/tips/tip_41.md
dev_tips/tips/tip_42.md
dev_tips/tips/tip_43.md
dev_tips/tips/tip_44.md
dev_tips/tips/tip_45.md
dev_tips/tips/tip_46.md
dev_tips/tips/tip_47.md
dev_tips/tips/tip_48.md
dev_tips/tips/tip_49.md
dev_tips/tips/tip_50.md
dev_tips/tips/tip_51.md
dev_tips/tips/tip_52.md
dev_tips/tips/tip_53.md
dev_tips/tips/tip_54.md
dev_tips/tips/tip_55.md
dev_tips/tips/tip_56.md
dev_tips/tips/tip_57.md
dev_tips/tips/tip_58.md
dev_tips/tips/tip_59.md
dev_tips/tips/tip_60.md
dev_tips/tips/tip_61.md
dev_tips/tips/tip_62.md
dev_tips/tips/tip_63.md
dev_tips/tips/tip_64.md
dev_tips/tips/tip_65.md
dev_tips/tips/tip_66.md
dev_tips/tips/tip_67.md
dev_tips/tips/tip_68.md
dev_tips/tips/tip_69.md
dev_tips/tips/tip_70.md
dev_tips/tips/tip_71.md
dev_tips/tips/tip_72.md
dev_tips/tips/tip_73.md
dev_tips/tips/tip_74.md
dev_tips/tips/tip_75.md
dev_tips/tips/tip_76.md
dev_tips/tips/tip_77.md
dev_tips/tips/tip_78.md
dev_tips/tips/tip_79.md
dev_tips/tips/tip_80.md
dev_tips-1.0.2.dist-info/LICENSE
dev_tips-1.0.2.dist-info/METADATA
dev_tips-1.0.2.dist-info/WHEEL
dev_tips-1.0.2.dist-info/top_level.txt
dev_tips-1.0.2.dist-info/RECORD
