Metadata-Version: 2.1
Name: dev-tips
Version: 1.0.2
Summary: CLI version of 97 Things Every Programmer Should Know
Home-page: https://github.com/igoryamamoto/dev-tips
Author: Ígor Yamamoto
Author-email: hello@igoryamamoto.com
License: UNKNOWN
Platform: UNKNOWN
Classifier: Programming Language :: Python :: 3
Classifier: License :: OSI Approved :: MIT License
Classifier: Operating System :: OS Independent
Requires-Python: >=3.7
